matsengrp_super_ai/__init__.py
matsengrp_super_ai/super_ai.py
matsengrp_super_ai-0.1.0.dist-info/METADATA
matsengrp_super_ai-0.1.0.dist-info/WHEEL
matsengrp_super_ai-0.1.0.dist-info/entry_points.txt
matsengrp_super_ai-0.1.0.dist-info/RECORD
